{
  "logoType": "text",
  "logoText": "Recipes fdghdfg",
  "logoTagline": "Collection fghdfghdfgh",
  "logoImage": "",
  "favicon": "",
  "footerCopyright": "2025 Recipes website. All rights reserved.",
  "footerVersion": "V0.1",
  "siteTitle": "Recipes website - Delicious Friendly Recipes",
  "siteDescription": "Discover amazing recipes from Guelma Team. Perfect for family meals, special occasions, and everyday cooking.",
  "siteDomain": "example.com",
  "siteUrl": "https://example.com",
  "siteEmail": "contact@example.com",
  "lastUpdated": "2025-10-17T13:03:13.796Z"
}